{
	"language": "en",
	"ignorePaths": [
		"src/lib/tailwind/generated/**",
		"static/**",
		"pnpm-lock.yaml",
		"package-lock.json",
		"yarn.lock",
		"package/**"
	],
	"dictionaries": ["html", "typescript", "softwareTerms", "companies"],
	"allowCompoundWords": true,
	"words": [
		"acumin",
		"autocollapse",
		"autohide",
		"blockquote",
		"changelogen",
		"consolas",
		"contenteditable",
		"dropzone",
		"ecommerce",
		"fieldset",
		"filesize",
		"fira",
		"flexbox",
		"futura",
		"Helvetica",
		"hoverable",
		"listbox",
		"nowrap",
		"nocheck",
		"postcss",
		"rgba",
		"stylesheet",
		"supabase",
		"testid",
		"textareas",
		"tsup",
		"unplugin",
		"uuidv",
		"Vercel",
		"vite",
		"Vitest"
	]
}
